molseeq/__init__.py
molseeq/molseeq_widget.py
molseeq/napari.yaml
molseeq/GUI/__init__.py
molseeq/GUI/gui.py
molseeq/funcs/__init__.py
molseeq/funcs/align_utils.py
molseeq/funcs/cluster_utils.py
molseeq/funcs/colocalize_utils.py
molseeq/funcs/events.py
molseeq/funcs/export_images_utils.py
molseeq/funcs/export_traces_utils.py
molseeq/funcs/filter_utils.py
molseeq/funcs/import_utils.py
molseeq/funcs/loc_utils.py
molseeq/funcs/picasso_detect.py
molseeq/funcs/plot_utils.py
molseeq/funcs/simple_analysis_utils.py
molseeq/funcs/temporal_filtering.py
molseeq/funcs/trace_compute_utils.py
molseeq/funcs/tracking_utils.py
molseeq/funcs/transform_utils.py
molseeq/funcs/undrift_utils.py
molseeq/funcs/utils_compute.py
napari_molseeq-1.0.8.dist-info/licenses/LICENSE
napari_molseeq-1.0.8.dist-info/METADATA
napari_molseeq-1.0.8.dist-info/WHEEL
napari_molseeq-1.0.8.dist-info/entry_points.txt
napari_molseeq-1.0.8.dist-info/top_level.txt
napari_molseeq-1.0.8.dist-info/RECORD
