Metadata-Version: 2.4
Name: napari-molseeq
Version: 1.0.8
Summary: A Napari plugin for extracting single molecule sequences from single/multi-channel SMLM microscopy data.
Author: Piers Turner
Author-email: piers.turner@physics.ox.ac.uk
License: 
Project-URL: Bug Tracker, https://github.com/piedrro/napari-molseeq/issues
Project-URL: Documentation, https://github.com/piedrro/napari-molseeq#README.md
Project-URL: Source Code, https://github.com/piedrro/napari-molseeq
Project-URL: User Support, https://github.com/piedrro/napari-molseeq/issues
Classifier: Development Status :: 2 - Pre-Alpha
Classifier: Framework :: napari
Classifier: Intended Audience :: Developers
Classifier: License :: OSI Approved :: BSD License
Classifier: Operating System :: OS Independent
Classifier: Programming Language :: Python
Classifier: Programming Language :: Python :: 3
Classifier: Programming Language :: Python :: 3 :: Only
Classifier: Programming Language :: Python :: 3.9
Classifier: Programming Language :: Python :: 3.10
Classifier: Programming Language :: Python :: 3.11
Classifier: Topic :: Scientific/Engineering :: Image Processing
Requires-Python: >=3.9
License-File: LICENSE
Requires-Dist: napari[all]==0.5.0
Requires-Dist: numpy
Requires-Dist: magicgui
Requires-Dist: qtpy
Requires-Dist: scipy
Requires-Dist: pyqtgraph
Requires-Dist: picassosr==0.7.3
Requires-Dist: pandas
Requires-Dist: matplotlib>=3.7.0
Requires-Dist: scipy
Requires-Dist: opencv-python
Requires-Dist: tqdm
Requires-Dist: originpro
Requires-Dist: pyqt5-tools
Requires-Dist: trackpy
Requires-Dist: shapely
Requires-Dist: astropy
Requires-Dist: mat4py
Provides-Extra: testing
Requires-Dist: tox; extra == "testing"
Requires-Dist: pytest; extra == "testing"
Requires-Dist: pytest-cov; extra == "testing"
Requires-Dist: pytest-qt; extra == "testing"
Requires-Dist: napari; extra == "testing"
Requires-Dist: pyqt5; extra == "testing"
Dynamic: license-file
